hepdata_lib/__init__.py
hepdata_lib/c_file_reader.py
hepdata_lib/helpers.py
hepdata_lib/hist_utils.py
hepdata_lib/root_utils.py
hepdata_lib-0.20.0.dist-info/licenses/LICENSE
hepdata_lib-0.20.0.dist-info/METADATA
hepdata_lib-0.20.0.dist-info/WHEEL
hepdata_lib-0.20.0.dist-info/top_level.txt
hepdata_lib-0.20.0.dist-info/RECORD
