Metadata-Version: 2.4
Name: hepdata_lib
Version: 0.20.0
Summary: Library for getting your data into HEPData
Home-page: https://github.com/HEPData/hepdata_lib
Author: Andreas Albert, Clemens Lange
Author-email: hepdata-lib@cern.ch
Project-URL: Documentation, https://hepdata-lib.readthedocs.io
Project-URL: Bug Reports, https://github.com/HEPData/hepdata_lib/issues
Project-URL: Source, https://github.com/HEPData/hepdata_lib
Keywords: HEPData physics OpenData
Classifier: Development Status :: 4 - Beta
Classifier: License :: OSI Approved :: MIT License
Classifier: Programming Language :: Python :: 3
Classifier: Programming Language :: Python :: 3.6
Classifier: Programming Language :: Python :: 3.7
Classifier: Programming Language :: Python :: 3.8
Classifier: Programming Language :: Python :: 3.9
Classifier: Programming Language :: Python :: 3.10
Classifier: Programming Language :: Python :: 3.11
Classifier: Programming Language :: Python :: 3.12
Classifier: Programming Language :: Python :: 3.13
Requires-Python: >=3.6
License-File: LICENSE
Requires-Dist: numpy
Requires-Dist: PyYAML>=4.0
Requires-Dist: hist
Requires-Dist: scipy
Requires-Dist: hepdata-validator>=0.3.5
Provides-Extra: test
Requires-Dist: ipykernel; extra == "test"
Requires-Dist: papermill; extra == "test"
Requires-Dist: pylint; extra == "test"
Requires-Dist: pytest; extra == "test"
Requires-Dist: pytest-cov; extra == "test"
Dynamic: author
Dynamic: author-email
Dynamic: classifier
Dynamic: description
Dynamic: description-content-type
Dynamic: home-page
Dynamic: keywords
Dynamic: license-file
Dynamic: project-url
Dynamic: provides-extra
Dynamic: requires-dist
Dynamic: requires-python
Dynamic: summary
